{"hiddenService":"armoryohajjhou5m.onion","dateScanned":"2019-04-04T23:42:42.9943542-04:00","online":false,"performedScans":["web","tls","ssh","irc","ricochet","ftp","smtp","mongodb","vnc","xmpp","bitcoin","bitcoin_test","litecoin","dogecoin"],"webDetected":true,"tlsDetected":false,"sshDetected":true,"ricochetDetected":false,"ircDetected":false,"ftpDetected":false,"smtpDetected":false,"bitcoinDetected":false,"mongodbDetected":false,"vncDetected":false,"xmppDetected":false,"skynetDetected":false,"crawls":{"http://armoryohajjhou5m.onion/":4197223642560636198,"http://armoryohajjhou5m.onion/css":7261542039326756490,"http://armoryohajjhou5m.onion/css/style.css":5984625926455374431,"http://armoryohajjhou5m.onion/img":6149952168363937803,"http://armoryohajjhou5m.onion/img/logo2.png":5599631501484832135,"http://armoryohajjhou5m.onion/private_key":6161508077723284920,"http://armoryohajjhou5m.onion/register.php":4180154742775644728,"http://armoryohajjhou5m.onion/server-status":4711079212342887620},"pgpKeys":null,"certificates":null,"bitcoinServices":{"bitcoin":{"detected":false,"userAgent":"","prototocolVersion":0,"onionPeers":null},"bitcoin_test":{"detected":false,"userAgent":"","prototocolVersion":0,"onionPeers":null},"dogecoin":{"detected":false,"userAgent":"","prototocolVersion":0,"onionPeers":null},"litecoin":{"detected":false,"userAgent":"","prototocolVersion":0,"onionPeers":null}},"sshKey":"0b:0a:34:a6:df:34:c9:00:d1:da:6c:47:47:06:5b:75","sshBanner":"SSH-2.0-OpenSSH_6.7p1 Debian-5+deb8u8\r\n","ftpFingerprint":"","ftpBanner":"","smtpFingerprint":"","smtpBanner":"","lastAction":"dogecoin","timedOut":false,"error":null,"identifierReport":{"privateKeyDetected":false,"foundApacheModStatus":false,"serverVersion":"","relatedOnionServices":null,"relatedOnionDomains":null,"ipAddresses":null,"emailAddresses":null,"analyticsIDs":null,"bitcoinAddresses":null,"linkedOnions":null,"openDirectories":null,"exifImages":null},"simpleReport":{"hiddenService":"armoryohajjhou5m.onion","risks":null}}
